dolomite_spatial/__init__.py
dolomite_spatial/read_spatial_experiment.py
dolomite_spatial/save_image.py
dolomite_spatial/save_spatial_experiment.py
dolomite_spatial-0.1.1.dist-info/licenses/LICENSE.txt
dolomite_spatial-0.1.1.dist-info/METADATA
dolomite_spatial-0.1.1.dist-info/WHEEL
dolomite_spatial-0.1.1.dist-info/top_level.txt
dolomite_spatial-0.1.1.dist-info/RECORD
