Metadata-Version: 2.4
Name: dolomite-spatial
Version: 0.1.1
Summary: Read and write Spatial Experiments to takane representations
Home-page: https://github.com/ArtifactDB/dolomite-spatial
Author: Jayaram Kancherla
Author-email: jayaram.kancherla@gmail.com
License: MIT
Project-URL: Documentation, https://github.com/ArtifactDB/dolomite-spatial
Platform: any
Classifier: Development Status :: 4 - Beta
Classifier: Programming Language :: Python
Requires-Python: >=3.9
License-File: LICENSE.txt
Requires-Dist: importlib-metadata; python_version < "3.8"
Requires-Dist: dolomite-base
Requires-Dist: dolomite-sce
Requires-Dist: dolomite-ranges>=0.2.1
Requires-Dist: spatialexperiment>=0.0.4
Requires-Dist: h5py
Provides-Extra: testing
Requires-Dist: setuptools; extra == "testing"
Requires-Dist: pytest; extra == "testing"
Requires-Dist: pytest-cov; extra == "testing"
Dynamic: license-file
